semantic_network/__init__.py
semantic_network/net.py
semantic_network/net_archivation.py
semantic_network/net_functions.py
semantic_network/net_search.py
semantic_network/query.py
semantic_network/script.py
semantic_network-0.2.0.dist-info/licenses/LICENCE
semantic_network-0.2.0.dist-info/METADATA
semantic_network-0.2.0.dist-info/WHEEL
semantic_network-0.2.0.dist-info/entry_points.txt
semantic_network-0.2.0.dist-info/top_level.txt
semantic_network-0.2.0.dist-info/RECORD
