Metadata-Version: 2.4
Name: semantic-network
Version: 0.2.0
Summary: Semantic network implementation
Author-email: Alexander Abramov <extremal.ru@gmail.com>
License: MIT
Project-URL: Homepage, https://github.com/avabr/semantic-network
Project-URL: Repository, https://github.com/avabr/semantic-network
Project-URL: Issues, https://github.com/avabr/semantic-network/issues
Keywords: rdf,semantic,network,graph
Classifier: Development Status :: 3 - Alpha
Classifier: Intended Audience :: Developers
Classifier: Intended Audience :: Science/Research
Classifier: License :: OSI Approved :: MIT License
Classifier: Programming Language :: Python :: 3
Classifier: Programming Language :: Python :: 3.7
Classifier: Programming Language :: Python :: 3.8
Classifier: Programming Language :: Python :: 3.9
Classifier: Programming Language :: Python :: 3.10
Classifier: Programming Language :: Python :: 3.11
Classifier: Programming Language :: Python :: 3.12
Classifier: Topic :: Software Development :: Libraries :: Python Modules
Classifier: Topic :: Scientific/Engineering :: Information Analysis
Requires-Python: >=3.7
License-File: LICENCE
Requires-Dist: networkx>=3.4.2
Dynamic: license-file
